opsqueue-0.30.3.dist-info/METADATA
opsqueue-0.30.3.dist-info/WHEEL
opsqueue/common.py
opsqueue/exceptions.py
opsqueue/__init__.py
opsqueue/producer.py
opsqueue/consumer.py
opsqueue/tracing.py
opsqueue/opsqueue_internal.cpython-312-x86_64-linux-gnu.so
opsqueue-0.30.3.dist-info/RECORD
